tests
tr064
