Metadata-Version: 2.1
Name: tr064
Version: 0.1.1
Summary: TR-064 python API
Home-page: https://github.com/bfueldner/tr064
Author: Benjamin Füldner
Author-email: benjamin@fueldner.net
License: MIT
Project-URL: Source, https://github.com/bfueldner/tr064
Project-URL: Bug Reports, https://github.com/bfueldner/tr064/issues
Keywords: TR-064 LAN DSL CPE configuration broadband forum home router
Platform: UNKNOWN
Classifier: Development Status :: 3 - Alpha
Classifier: Intended Audience :: Developers
Classifier: Programming Language :: Python :: 3
Classifier: Programming Language :: Python :: 3.6
Classifier: Programming Language :: Python :: 3.7
Classifier: Programming Language :: Python :: 3.8
Classifier: License :: OSI Approved :: MIT License
Classifier: Operating System :: OS Independent
Classifier: Topic :: Software Development :: Libraries :: Python Modules
Requires-Python: >=3.6
